datetimeparser/__init__.py
datetimeparser/baseclasses.py
datetimeparser/datetimeparser.py
datetimeparser/enums.py
datetimeparser/evaluator.py
datetimeparser/evaluatormethods.py
datetimeparser/formulars.py
datetimeparser/parser.py
datetimeparser/parsermethods.py
python_datetimeparser-0.4rc0.dist-info/LICENSE
python_datetimeparser-0.4rc0.dist-info/METADATA
python_datetimeparser-0.4rc0.dist-info/WHEEL
python_datetimeparser-0.4rc0.dist-info/top_level.txt
python_datetimeparser-0.4rc0.dist-info/RECORD
