Metadata-Version: 2.1
Name: python-datetimeparser
Version: 0.4rc0
Summary: A parser library built for parsing the english language into datetime objects.
Home-page: https://github.com/aridevelopment-de/datetimeparser
Download-URL: https://github.com/aridevelopment-de/datetimeparser/archive/v0.1e.tar.gz
Author: Ari24
Author-email: ari.publicmail@gmail.com
License: MIT
Keywords: datetime,parser,parsing,grammar,datetime-parser
Platform: UNKNOWN
Classifier: Development Status :: 4 - Beta
Classifier: Intended Audience :: Developers
Classifier: Topic :: Software Development :: Build Tools
Classifier: License :: OSI Approved :: MIT License
Classifier: Programming Language :: Python :: 3.7
Classifier: Programming Language :: Python :: 3.8
Classifier: Programming Language :: Python :: 3.9
Classifier: Programming Language :: Python :: 3.10
License-File: LICENSE
Requires-Dist: python-dateutil
Requires-Dist: pytz
Requires-Dist: typing
